eventflow/__init__.py
eventflow/core/__init__.py
eventflow/core/events.py
eventflow/core/protocols.py
eventflow/core/types.py
eventflow/patterns/__init__.py
eventflow/patterns/inbox/__init__.py
eventflow/patterns/inbox/consumer.py
eventflow/patterns/inbox/models.py
eventflow/patterns/inbox/repository.py
eventflow/patterns/outbox/__init__.py
eventflow/patterns/outbox/publisher.py
eventflow/transports/__init__.py
eventflow/transports/redis_streams.py
eventflow/utils/__init__.py
eventflow/utils/errors.py
python_eventflow-1.0.1.dist-info/LICENSE
python_eventflow-1.0.1.dist-info/METADATA
python_eventflow-1.0.1.dist-info/WHEEL
python_eventflow-1.0.1.dist-info/RECORD
