Metadata-Version: 2.1
Name: python-eventflow
Version: 1.0.1
Summary: Production-ready event-driven architecture toolkit with Transactional Inbox/Outbox patterns
Home-page: https://github.com/parhamdavari/eventflow
License: MIT
Keywords: event-driven,microservices,inbox,outbox,redis-streams,reliable-messaging
Author: Parham Davari
Author-email: parham.davarii@gmail.com
Requires-Python: >=3.10,<4.0
Classifier: Development Status :: 5 - Production/Stable
Classifier: Intended Audience :: Developers
Classifier: License :: OSI Approved :: MIT License
Classifier: Programming Language :: Python :: 3
Classifier: Programming Language :: Python :: 3.10
Classifier: Programming Language :: Python :: 3.11
Classifier: Programming Language :: Python :: 3.12
Classifier: Programming Language :: Python :: 3.13
Classifier: Topic :: Software Development :: Libraries :: Python Modules
Classifier: Topic :: System :: Distributed Computing
Requires-Dist: redis (>=5.0,<6.0)
Requires-Dist: sqlalchemy (>=2.0,<3.0)
Project-URL: Documentation, https://github.com/parhamdavari/eventflow
Project-URL: Repository, https://github.com/parhamdavari/eventflow
